{"title":"Art","description":""} 
{"title":"Natural Sciences","description":""} 
{"title":"Music","description":""} 
{"title":"Games","description":""} 
{"title":"Technology","description":""}
{"title":"Computing","description":""}
{"title":"Design","description":""}
{"title":"History","description":""}
{"title":"Social Sciences","description":""}
{"title":"Literature","description":""}
{"title":"Politics","description":""}
{"title":"News","description":""}
{"title":"Sports","description":""}
{"title":"TV & Film","description":""}
{"title":"Business","description":""}
{"title":"Fashion","description":""}
{"title":"Other","description":""} 